gluster_georep_tools/__init__.py
gluster_georep_tools/_version.py
gluster_georep_tools/setup/__init__.py
gluster_georep_tools/setup/cli.py
gluster_georep_tools/status/__init__.py
gluster_georep_tools/status/cli.py
gluster_georep_tools-0.5.1.dist-info/LICENSE
gluster_georep_tools-0.5.1.dist-info/METADATA
gluster_georep_tools-0.5.1.dist-info/WHEEL
gluster_georep_tools-0.5.1.dist-info/entry_points.txt
gluster_georep_tools-0.5.1.dist-info/top_level.txt
gluster_georep_tools-0.5.1.dist-info/RECORD
